netfshare/__init__.py
netfshare/__main__.py
netfshare/config.py
netfshare/netfshare.py
netfshare/static/bulma.css
netfshare/static/icon.png
netfshare/templates/admin.html
netfshare/templates/base.html
netfshare/templates/identify.html
netfshare/templates/list_dirs.html
netfshare/templates/manage_session.html
netfshare/templates/upload.html
netfshare/translations/sl/LC_MESSAGES/messages.mo
netfshare/translations/sl/LC_MESSAGES/messages.po
netfshare-0.5.dist-info/METADATA
netfshare-0.5.dist-info/WHEEL
netfshare-0.5.dist-info/licenses/LICENSE.txt
netfshare-0.5.dist-info/RECORD
