Metadata-Version: 2.4
Name: netfshare
Version: 0.5
Summary: A simple flask-based file sharing / distribution service
Project-URL: Homepage, https://github.com/domengorjup/netfsharet
Project-URL: Issues, https://github.com/domengorjup/netfshare/issues
Author-email: Domen Gorjup <domen_gorjup@hotmail.com>
License-File: LICENSE.txt
Classifier: License :: OSI Approved :: MIT License
Classifier: Operating System :: OS Independent
Classifier: Programming Language :: Python :: 3
Requires-Python: >=3.10
Requires-Dist: flask-babel>=4.0.0
Requires-Dist: flask-socketio>=5.3.6
Requires-Dist: flask-sqlalchemy>=3.1.0
Requires-Dist: flask>=3.0.0
Requires-Dist: python-dotenv>=1.0.1
Requires-Dist: pythonping>=1.1.4
